topsis/__init__.py
topsis/__main__.py
topsis/app.py
topsis_gaurav_102303493-1.0.6.dist-info/METADATA
topsis_gaurav_102303493-1.0.6.dist-info/WHEEL
topsis_gaurav_102303493-1.0.6.dist-info/entry_points.txt
topsis_gaurav_102303493-1.0.6.dist-info/top_level.txt
topsis_gaurav_102303493-1.0.6.dist-info/RECORD
