Metadata-Version: 2.4
Name: topsis-gaurav-102303493
Version: 1.0.6
Summary: A Python package implementing the TOPSIS method for multi-criteria decision making.
Author: Gaurav Prakash Srivastava
Author-email: gsrivastava_be23@thapar.edu
License: MIT
Requires-Dist: pandas
Requires-Dist: numpy
Requires-Dist: argparse
Dynamic: author
Dynamic: author-email
Dynamic: description
Dynamic: description-content-type
Dynamic: license
Dynamic: requires-dist
Dynamic: summary
